{
  "optimization_results": [
    {
      "batch_id": 4,
      "domain": "TEMPLATE",
      "processed_tags": 8,
      "spec_code_mappings": 6,
      "code_test_mappings": 6,
      "test_doc_mappings": 6,
      "repaired_chains": 6,
      "mappings": {
        "spec_code": {
          "@CODE:TEMPLATE-PROCESSING-001": "SPEC-TEMPLATE-4-001",
          "@CODE:TEMPLATE-CONFIG-001": "SPEC-TEMPLATE-4-002",
          "@CODE:TEMPLATE-001": "SPEC-TEMPLATE-4-003",
          "@CODE:TEMPLATE-LANGUAGES-001": "SPEC-TEMPLATE-4-004",
          "@CODE:TEMPLATE-BACKUP-001": "SPEC-TEMPLATE-4-005",
          "@CODE:TEMPLATE-MODULE-001": "SPEC-TEMPLATE-4-006"
        },
        "code_test": {
          "@CODE:TEMPLATE-PROCESSING-001": "@TEST:TEMPLATE-BACKUP-001",
          "@CODE:TEMPLATE-CONFIG-001": "@TEST:TEMPLATE-CONFIG-001",
          "@CODE:TEMPLATE-001": "@TEST:TEMPLATE-LANGUAGES-001",
          "@CODE:TEMPLATE-LANGUAGES-001": "@TEST:TEMPLATE-MODULE-001",
          "@CODE:TEMPLATE-BACKUP-001": "@TEST:TEMPLATE-MERGER-001",
          "@CODE:TEMPLATE-MODULE-001": "@TEST:TEMPLATE-PROCESSING-001"
        },
        "test_doc": {
          "@TEST:TEMPLATE-BACKUP-001": "DOC-TEMPLATE-001",
          "@TEST:TEMPLATE-CONFIG-001": "DOC-TEMPLATE-002",
          "@TEST:TEMPLATE-LANGUAGES-001": "DOC-TEMPLATE-003",
          "@TEST:TEMPLATE-MODULE-001": "DOC-OFFLINE-001",
          "@TEST:TEMPLATE-MERGER-001": "DOC-OFFLINE-002",
          "@TEST:TEMPLATE-PROCESSING-001": "DOC-OFFLINE-003"
        }
      }
    },
    {
      "batch_id": 2,
      "domain": "CORE",
      "processed_tags": 6,
      "spec_code_mappings": 1,
      "code_test_mappings": 1,
      "test_doc_mappings": 1,
      "repaired_chains": 1,
      "mappings": {
        "spec_code": {
          "@CODE:CORE-001": "SPEC-CORE-2-001"
        },
        "code_test": {
          "@CODE:CORE-001": "@TEST:CORE-PROJECT-001"
        },
        "test_doc": {
          "@TEST:CORE-PROJECT-001": "DOC-MAJOR-001"
        }
      }
    },
    {
      "batch_id": 1,
      "domain": "OFFLINE",
      "processed_tags": 6,
      "spec_code_mappings": 4,
      "code_test_mappings": 4,
      "test_doc_mappings": 4,
      "repaired_chains": 4,
      "mappings": {
        "spec_code": {
          "@CODE:OFFLINE-TIMEOUT-001": "SPEC-OFFLINE-1-001",
          "@CODE:OFFLINE-AVAILABLE-001": "SPEC-OFFLINE-1-002",
          "@CODE:OFFLINE-CACHE-VALID-001": "SPEC-OFFLINE-1-003",
          "@CODE:OFFLINE-UNAVAILABLE-001": "SPEC-OFFLINE-1-004"
        },
        "code_test": {
          "@CODE:OFFLINE-TIMEOUT-001": "@TEST:OFFLINE-MODE-001",
          "@CODE:OFFLINE-AVAILABLE-001": "@TEST:OFFLINE-AVAILABLE-001",
          "@CODE:OFFLINE-CACHE-VALID-001": "@TEST:OFFLINE-001",
          "@CODE:OFFLINE-UNAVAILABLE-001": "@TEST:OFFLINE-TIMEOUT-001"
        },
        "test_doc": {
          "@TEST:OFFLINE-MODE-001": "DOC-NO-001",
          "@TEST:OFFLINE-AVAILABLE-001": "DOC-NO-002",
          "@TEST:OFFLINE-001": "DOC-NO-003",
          "@TEST:OFFLINE-TIMEOUT-001": "DOC-CACHE-001"
        }
      }
    },
    {
      "batch_id": 3,
      "domain": "NO",
      "processed_tags": 4,
      "spec_code_mappings": 2,
      "code_test_mappings": 2,
      "test_doc_mappings": 2,
      "repaired_chains": 2,
      "mappings": {
        "spec_code": {
          "@CODE:NO-TEST-001": "SPEC-NO-3-001",
          "@CODE:NO-CODE-001": "SPEC-NO-3-002"
        },
        "code_test": {
          "@CODE:NO-TEST-001": "@TEST:NO-DOC-001",
          "@CODE:NO-CODE-001": "@TEST:NO-IMPL-001"
        },
        "test_doc": {
          "@TEST:NO-DOC-001": "DOC-CORE-001",
          "@TEST:NO-IMPL-001": "DOC-CORE-002"
        }
      }
    }
  ],
  "optimization_report": {
    "optimization_summary": {
      "initial_score": 0.030959752321981424,
      "final_score": 0.04024767801857585,
      "improvement": 0.009287925696594427,
      "achievement_status": "IN_PROGRESS",
      "target_score": 0.85,
      "improvement_ratio": 4.7350209433618655
    },
    "processing_metrics": {
      "total_batches": 4,
      "completed_batches": 4,
      "execution_time_minutes": 0,
      "execution_time_seconds": 0,
      "total_repaired_chains": 13,
      "total_processed_tags": 24,
      "total_mappings_created": 12
    },
    "optimization_details": {
      "optimization_config": {
        "batch_size": 20,
        "max_workers": 8,
        "target_score": 0.85,
        "optimization_rounds": 3,
        "enable_parallel_processing": true,
        "enable_smart_mapping": true,
        "enable_auto_validation": true
      },
      "results_summary": {
        "batches_processed": 4,
        "average_chains_per_batch": 3.25,
        "efficiency_score": 0.5416666666666666
      }
    },
    "achievement_analysis": {
      "goal_achieved": false,
      "gap_to_target": 0.8097523219814241,
      "recommended_actions": [
        "전체 시스템 재구축 필요",
        "정기적인 무결성 검사 스케줄링",
        "자동화된 감시 시스템 구축"
      ]
    }
  },
  "progress_summary": {
    "total_batches": 4,
    "completed_batches": 4,
    "repaired_chains": 13,
    "processed_tags": 24
  },
  "optimized_at": "2025-11-05"
}